router_test_kit/__init__.py
router_test_kit/connection.py
router_test_kit/device.py
router_test_kit/logger.py
router_test_kit/static_utils.py
router_test_kit-0.1.3.dist-info/LICENSE
router_test_kit-0.1.3.dist-info/METADATA
router_test_kit-0.1.3.dist-info/WHEEL
router_test_kit-0.1.3.dist-info/top_level.txt
router_test_kit-0.1.3.dist-info/RECORD
