Metadata-Version: 2.1
Name: router-test-kit
Version: 0.1.3
Summary: A framework for remotely testing routers, physical or virtual.
Home-page: https://github.com/alex-anast/router-test-kit
Author: Alexandros Anastasiou, alex-anast
Author-email: anastasioyaa@gmail.com
Classifier: Programming Language :: Python :: 3
Classifier: License :: OSI Approved :: MIT License
Classifier: Operating System :: POSIX :: Linux
Requires-Python: >=3.7
License-File: LICENSE
Requires-Dist: exceptiongroup ==1.2.0
Requires-Dist: importlib-metadata ==6.7.0
Requires-Dist: iniconfig ==2.0.0
Requires-Dist: packaging ==23.2
Requires-Dist: pluggy ==1.2.0
Requires-Dist: pytest-rerunfailures ==13.0
Requires-Dist: pytest-sugar ==1.0.0
Requires-Dist: pytest ==7.4.4
Requires-Dist: termcolor ==2.3.0
Requires-Dist: tomli ==2.0.1
Requires-Dist: typing-extensions ==4.7.1
Requires-Dist: zipp ==3.15.0
